<?xml version="1.0" encoding="ISO-8859-1"?>
<ITRETURN:ITR xmlns:ITR1FORM="http://incometaxindiaefiling.gov.in/ITR1" xmlns:ITRETURN="http://incometaxindiaefiling.gov.in/main"
xmlns:ITRForm="http://incometaxindiaefiling.gov.in/master"
xmlns:xsi="http://www.w3.org/2001/XMLSchema-instance">
<ITR1FORM:ITR1>
<ITRForm:CreationInfo>
<ITRForm:SWVersionNo>1.81</ITRForm:SWVersionNo>
<ITRForm:SWCreatedBy>Smartbiz Technologies</ITRForm:SWCreatedBy>
<ITRForm:XMLCreatedBy>Smartbiz Technologies</ITRForm:XMLCreatedBy>
<ITRForm:XMLCreationDate>2014-06-28</ITRForm:XMLCreationDate>
<ITRForm:IntermediaryCity>Amritsar</ITRForm:IntermediaryCity>
</ITRForm:CreationInfo>
<ITRForm:Form_ITR1>
<ITRForm:FormName>ITR-1</ITRForm:FormName>
<ITRForm:Description>For Indls having Income from Salary, Pension, family pension and Interest</ITRForm:Description>
<ITRForm:AssessmentYear>2014</ITRForm:AssessmentYear>
<ITRForm:SchemaVer>Ver1.0</ITRForm:SchemaVer>
<ITRForm:FormVer>Ver1.0</ITRForm:FormVer>
</ITRForm:Form_ITR1>
<ITRForm:PersonalInfo>
<ITRForm:AssesseeName>
<ITRForm:SurNameOrOrgName>LAVLEEN</ITRForm:SurNameOrOrgName>
</ITRForm:AssesseeName>
<ITRForm:PAN>AADPL6233H</ITRForm:PAN>
<ITRForm:Address>
<ITRForm:ResidenceNo>H.NO.225</ITRForm:ResidenceNo>
<ITRForm:RoadOrStreet>OPP. DR. NIRMAN SINGH KHURLA SINGH</ITRForm:RoadOrStreet>
<ITRForm:LocalityOrArea>JALANDHAR</ITRForm:LocalityOrArea>
<ITRForm:CityOrTownOrDistrict>JALANDHAR</ITRForm:CityOrTownOrDistrict>
<ITRForm:StateCode>26</ITRForm:StateCode>
<ITRForm:CountryCode>91</ITRForm:CountryCode>
<ITRForm:PinCode>144014</ITRForm:PinCode>
<ITRForm:MobileNo>9814165465</ITRForm:MobileNo>
<ITRForm:EmailAddress>vijay.0135@yahoo.in</ITRForm:EmailAddress>
</ITRForm:Address>
<ITRForm:DOB>1974-11-25</ITRForm:DOB>
<ITRForm:EmployerCategory>OTH</ITRForm:EmployerCategory>
<ITRForm:Gender>F</ITRForm:Gender>
<ITRForm:Status>I</ITRForm:Status>
</ITRForm:PersonalInfo>
<ITRForm:FilingStatus>
<ITRForm:DesigOfficerWardorCircle></ITRForm:DesigOfficerWardorCircle>
<ITRForm:ReturnFileSec>11</ITRForm:ReturnFileSec>
<ITRForm:ReturnType>O</ITRForm:ReturnType>
<ITRForm:ResidentialStatus>RES</ITRForm:ResidentialStatus>
<ITRForm:TaxStatus>TR</ITRForm:TaxStatus>
<ITRForm:PortugeseCC5A>N</ITRForm:PortugeseCC5A>
</ITRForm:FilingStatus>
<ITRForm:ITR1_IncomeDeductions>
<ITRForm:IncomeFromSal>513501</ITRForm:IncomeFromSal>
<ITRForm:TypeOfHP>S</ITRForm:TypeOfHP>
<ITRForm:TotalIncomeOfHP>-30160</ITRForm:TotalIncomeOfHP>
<ITRForm:IncomeOthSrc>0</ITRForm:IncomeOthSrc>
<ITRForm:GrossTotIncome>483341</ITRForm:GrossTotIncome>
<ITRForm:UsrDeductUndChapVIA>
<ITRForm:Section80C>100000</ITRForm:Section80C>
<ITRForm:TotalChapVIADeductions>100000</ITRForm:TotalChapVIADeductions>
</ITRForm:UsrDeductUndChapVIA>
<ITRForm:DeductUndChapVIA>
<ITRForm:Section80C>100000</ITRForm:Section80C>
<ITRForm:TotalChapVIADeductions>100000</ITRForm:TotalChapVIADeductions>
</ITRForm:DeductUndChapVIA>
<ITRForm:TotalIncome>383340</ITRForm:TotalIncome>
</ITRForm:ITR1_IncomeDeductions>
<ITRForm:ITR1_TaxComputation>
<ITRForm:TotalTaxPayable>18334</ITRForm:TotalTaxPayable>
<ITRForm:Rebate87A>2000</ITRForm:Rebate87A>
<ITRForm:TaxPayableOnRebate>16334</ITRForm:TaxPayableOnRebate>
<ITRForm:SurchargeOnAboveCrore>0</ITRForm:SurchargeOnAboveCrore>
<ITRForm:EducationCess>490</ITRForm:EducationCess>
<ITRForm:GrossTaxLiability>16824</ITRForm:GrossTaxLiability>
<ITRForm:Section89>0</ITRForm:Section89>
<ITRForm:NetTaxLiability>16824</ITRForm:NetTaxLiability>
<ITRForm:TotalIntrstPay>0</ITRForm:TotalIntrstPay>
<ITRForm:IntrstPay>
<ITRForm:IntrstPayUs234A>0</ITRForm:IntrstPayUs234A>
<ITRForm:IntrstPayUs234B>0</ITRForm:IntrstPayUs234B>
<ITRForm:IntrstPayUs234C>0</ITRForm:IntrstPayUs234C>
</ITRForm:IntrstPay>
<ITRForm:TotTaxPlusIntrstPay>16824</ITRForm:TotTaxPlusIntrstPay>
</ITRForm:ITR1_TaxComputation>
<ITRForm:TaxPaid>
<ITRForm:TaxesPaid>
<ITRForm:AdvanceTax>0</ITRForm:AdvanceTax>
<ITRForm:TDS>17227</ITRForm:TDS>
<ITRForm:SelfAssessmentTax>0</ITRForm:SelfAssessmentTax>
<ITRForm:TotalTaxesPaid>17227</ITRForm:TotalTaxesPaid>
</ITRForm:TaxesPaid>
<ITRForm:BalTaxPayable>0</ITRForm:BalTaxPayable>
</ITRForm:TaxPaid>
<ITRForm:Refund>
<ITRForm:RefundDue>400</ITRForm:RefundDue>
<ITRForm:BankAccountNumber>65036443993</ITRForm:BankAccountNumber>
<ITRForm:DepositToBankAccount>
<ITRForm:IFSCCode>STBP0000977</ITRForm:IFSCCode>
<ITRForm:BankAccountType>SAV</ITRForm:BankAccountType>
</ITRForm:DepositToBankAccount>
</ITRForm:Refund>
<ITRForm:TDSonSalaries>
<ITRForm:TDSonSalary>
<ITRForm:EmployerOrDeductorOrCollectDetl>
<ITRForm:TAN>JLDB00375E</ITRForm:TAN>
<ITRForm:EmployerOrDeductorOrCollecterName>BPEO JALANDHAR EAST</ITRForm:EmployerOrDeductorOrCollecterName>
</ITRForm:EmployerOrDeductorOrCollectDetl>
<ITRForm:IncChrgSal>483341</ITRForm:IncChrgSal>
<ITRForm:TotalTDSSal>17227</ITRForm:TotalTDSSal>
</ITRForm:TDSonSalary>
</ITRForm:TDSonSalaries>
<ITR1FORM:TaxExmpIntInc>0</ITR1FORM:TaxExmpIntInc>
<ITRForm:Verification>
<ITRForm:Declaration>
<ITRForm:AssesseeVerName>LAVLEEN</ITRForm:AssesseeVerName>
<ITRForm:FatherName>SH.BISHAN SINGH</ITRForm:FatherName>
<ITRForm:AssesseeVerPAN>AADPL6233H</ITRForm:AssesseeVerPAN>
</ITRForm:Declaration>
<ITRForm:Place>JALANDHAR</ITRForm:Place>
<ITRForm:Date>2014-06-28</ITRForm:Date>
</ITRForm:Verification>
</ITR1FORM:ITR1>
</ITRETURN:ITR>
